avcord/__init__.py
avcord/encoder.py
avcord/errors.py
avcord/sources.py
avcord/stream.py
av_discord-0.0.1.dist-info/LICENSE
av_discord-0.0.1.dist-info/METADATA
av_discord-0.0.1.dist-info/WHEEL
av_discord-0.0.1.dist-info/top_level.txt
av_discord-0.0.1.dist-info/RECORD
