Metadata-Version: 2.1
Name: av-discord
Version: 0.0.1
Summary: PyAV audio sources for discord.py, pycord, and disnake
Home-page: https://github.com/mansuf/av-cord
Author: Rahman Yusuf
Author-email: danipart4@gmail.com
License: MIT
Keywords: discord,audio
Classifier: Development Status :: 4 - Beta
Classifier: Intended Audience :: Developers
Classifier: License :: OSI Approved :: MIT License
Classifier: Programming Language :: Python :: 3 :: Only
Classifier: Programming Language :: Python :: 3
Classifier: Programming Language :: Python :: 3.8
Classifier: Programming Language :: Python :: 3.9
Classifier: Programming Language :: Python :: 3.10
Requires-Python: >=3.8
License-File: LICENSE
Requires-Dist: av
Provides-Extra: docs
Requires-Dist: sphinx (<5) ; extra == 'docs'
Requires-Dist: furo ; extra == 'docs'
Requires-Dist: myst-parser[linkify] ; extra == 'docs'
